mc10_parser/__init__.py
mc10_parser/dataio.py
mc10_parser/dictio.py
mc10_parser/session.py
mc10_parser-0.0.5.dist-info/LICENSE
mc10_parser-0.0.5.dist-info/METADATA
mc10_parser-0.0.5.dist-info/WHEEL
mc10_parser-0.0.5.dist-info/top_level.txt
mc10_parser-0.0.5.dist-info/RECORD
