Metadata-Version: 2.1
Name: mc10-parser
Version: 0.0.5
Summary: Data IO and parsing for MC10 BioStamp Sensors
Home-page: UNKNOWN
Author: Sabar Dasgupta
Author-email: sdasgupta@epilepsyco.com
License: MIT,
Platform: UNKNOWN
Requires-Python: >=3.7.3
Requires-Dist: boto3
Requires-Dist: numpy
Requires-Dist: pandas
Requires-Dist: pytz
Requires-Dist: requests
Requires-Dist: s3fs
